nolang_mcp/__init__.py
nolang_mcp/api_client.py
nolang_mcp/config.py
nolang_mcp/models.py
nolang_mcp/runner/run_http.py
nolang_mcp/runner/run_stdio.py
nolang_mcp/server.py
nolang_mcp-0.0.2.dist-info/WHEEL
nolang_mcp-0.0.2.dist-info/entry_points.txt
nolang_mcp-0.0.2.dist-info/METADATA
nolang_mcp-0.0.2.dist-info/RECORD
