Metadata-Version: 2.3
Name: nolang-mcp
Version: 0.0.2
Summary: NoLang MCP Server for AI Video Generation
Keywords: nolang,mcp,claude,ai,video
Author: Mavericks, inc.
Author-email: Mavericks, inc. <support.nolang@mvrks.co.jp>
License: MIT
Requires-Dist: fastmcp>=2.11.0
Requires-Dist: pydantic>=2.0.0
Requires-Dist: httpx>=0.27.0
Requires-Dist: python-dotenv>=1.0.0
Requires-Dist: ruff ; extra == 'dev'
Requires-Dist: uv ; extra == 'dev'
Requires-Dist: mypy ; extra == 'dev'
Requires-Python: >=3.12
Provides-Extra: dev
